{
  "trend": "Month Ago",
  "category": "culture",
  "platforms": {
    "x": true
  },
  "platform_count": 1,
  "metrics": {
    "google": {
      "searches": "0",
      "raw": 0
    },
    "x": {
      "posts": "77.6K",
      "reposts": "11.9K",
      "raw_posts": 77644,
      "raw_reposts": 11855
    },
    "tiktok": {
      "views": "0",
      "videos": "0",
      "raw_views": 0
    },
    "instagram": {
      "posts": "0",
      "reach": "0",
      "raw_posts": 0
    }
  },
  "signal_score": 55,
  "momentum": "stable",
  "lifecycle": "peak",
  "locations": [
    "global"
  ],
  "related_trends": [],
  "analysis": {
    "headline": "Viral Trend Takes the Internet by Storm: Analyzing the Craze",
    "summary": "A month-old trend has suddenly exploded across multiple online platforms, captivating users and sparking widespread discussion. This surge in popularity sheds light on the evolving digital landscape and the factors that drive user engagement.",
    "origin_story": "The trend first emerged on x platform, where users began posting and sharing content related to the topic in large numbers.",
    "expert_analysis": "This trend reflects the growing influence of internet subcultures and their ability to drive mainstream cultural discourse. The rapid spread of the content suggests a collective desire for content that resonates with specific communities and taps into shared experiences or interests.",
    "impact": "The trend's viral nature has the potential to shape broader conversations and even influence real-world behaviors or attitudes.",
    "status": "viral"
  },
  "timestamp": "2026-02-07T20:57:16.183543+00:00",
  "history": [
    {
      "timestamp": "2026-02-06T11:47:19.088124+00:00",
      "signal_score": 55
    },
    {
      "timestamp": "2026-02-06T12:10:43.181652+00:00",
      "signal_score": 55
    },
    {
      "timestamp": "2026-02-06T12:20:38.389487+00:00",
      "signal_score": 55
    },
    {
      "timestamp": "2026-02-06T12:25:56.306737+00:00",
      "signal_score": 55
    },
    {
      "timestamp": "2026-02-06T15:06:07.843256+00:00",
      "signal_score": 55
    },
    {
      "timestamp": "2026-02-06T17:31:40.499203+00:00",
      "signal_score": 55
    },
    {
      "timestamp": "2026-02-06T19:50:12.808109+00:00",
      "signal_score": 55
    },
    {
      "timestamp": "2026-02-06T22:53:41.391338+00:00",
      "signal_score": 55
    },
    {
      "timestamp": "2026-02-06T23:54:00.305831+00:00",
      "signal_score": 55
    },
    {
      "timestamp": "2026-02-07T04:55:07.844630+00:00",
      "signal_score": 55
    },
    {
      "timestamp": "2026-02-07T07:57:46.045056+00:00",
      "signal_score": 55
    },
    {
      "timestamp": "2026-02-07T09:03:02.144004+00:00",
      "signal_score": 55
    },
    {
      "timestamp": "2026-02-07T09:58:16.346219+00:00",
      "signal_score": 55
    },
    {
      "timestamp": "2026-02-07T10:58:19.809876+00:00",
      "signal_score": 55
    },
    {
      "timestamp": "2026-02-07T11:45:23.053140+00:00",
      "signal_score": 55
    },
    {
      "timestamp": "2026-02-07T11:59:28.406983+00:00",
      "signal_score": 55
    },
    {
      "timestamp": "2026-02-07T13:57:26.921498+00:00",
      "signal_score": 55
    },
    {
      "timestamp": "2026-02-07T15:52:52.999589+00:00",
      "signal_score": 55
    },
    {
      "timestamp": "2026-02-07T17:02:12.100805+00:00",
      "signal_score": 55
    },
    {
      "timestamp": "2026-02-07T17:19:40.263718+00:00",
      "signal_score": 55
    },
    {
      "timestamp": "2026-02-07T17:57:08.053354+00:00",
      "signal_score": 55
    },
    {
      "timestamp": "2026-02-07T19:06:05.266696+00:00",
      "signal_score": 55
    },
    {
      "timestamp": "2026-02-07T19:49:48.683234+00:00",
      "signal_score": 55
    },
    {
      "timestamp": "2026-02-07T20:57:16.183563+00:00",
      "signal_score": 55
    }
  ]
}