{
  "trend": "nfl trending",
  "category": "sports",
  "platforms": {
    "google": true
  },
  "platform_count": 1,
  "metrics": {
    "google": {
      "searches": "253.2K",
      "raw": 253224
    },
    "x": {
      "posts": "0",
      "reposts": "0",
      "raw_posts": 0,
      "raw_reposts": 0
    },
    "tiktok": {
      "views": "0",
      "videos": "0",
      "raw_views": 0
    },
    "instagram": {
      "posts": "0",
      "reach": "0",
      "raw_posts": 0
    }
  },
  "signal_score": 50,
  "momentum": "stable",
  "lifecycle": "peak",
  "locations": [
    "global"
  ],
  "related_trends": [
    "nfl trending",
    "nfl trending news",
    "nfl trending players",
    "nfl trending topics",
    "nfl trending twitter"
  ],
  "analysis": {
    "headline": "NFL Dominates Google Searches as Fans Eagerly Await Season Kickoff",
    "summary": "With the NFL regular season just around the corner, fans are scouring the internet for the latest news, updates, and rumors about their favorite teams and players. This surge in Google searches reflects the growing excitement and anticipation among football enthusiasts.",
    "origin_story": "The increased interest in the NFL has been building up over the past few weeks as preseason games and roster announcements have captured the attention of dedicated fans.",
    "expert_analysis": "The NFL's enduring popularity and the intense passion of its fanbase are driving this trend. Football remains one of the most watched and discussed sports in the United States, with millions of fans eagerly following every development in the lead-up to the new season.",
    "impact": "This spike in Google searches is indicative of the widespread interest and engagement with the NFL, which will likely translate into high viewership and engagement once the regular season kicks off.",
    "status": "rising"
  },
  "timestamp": "2026-02-08T15:00:12.626217+00:00",
  "history": [
    {
      "timestamp": "2026-02-07T10:58:40.398998+00:00",
      "signal_score": 50
    },
    {
      "timestamp": "2026-02-07T14:58:23.475732+00:00",
      "signal_score": 50
    },
    {
      "timestamp": "2026-02-07T17:02:46.063511+00:00",
      "signal_score": 50
    },
    {
      "timestamp": "2026-02-07T20:57:46.732852+00:00",
      "signal_score": 50
    },
    {
      "timestamp": "2026-02-07T23:01:05.007576+00:00",
      "signal_score": 50
    },
    {
      "timestamp": "2026-02-08T09:59:45.129237+00:00",
      "signal_score": 50
    },
    {
      "timestamp": "2026-02-08T15:00:12.626233+00:00",
      "signal_score": 50
    }
  ]
}