{
  "trend": "super bowl trending",
  "category": "sports",
  "platforms": {
    "google": true
  },
  "platform_count": 1,
  "metrics": {
    "google": {
      "searches": "286.1K",
      "raw": 286116
    },
    "x": {
      "posts": "0",
      "reposts": "0",
      "raw_posts": 0,
      "raw_reposts": 0
    },
    "tiktok": {
      "views": "0",
      "videos": "0",
      "raw_views": 0
    },
    "instagram": {
      "posts": "0",
      "reach": "0",
      "raw_posts": 0
    }
  },
  "signal_score": 50,
  "momentum": "stable",
  "lifecycle": "peak",
  "locations": [
    "global"
  ],
  "related_trends": [
    "super bowl trending",
    "super bowl trending twitter",
    "super bowl trending song"
  ],
  "analysis": {
    "headline": "The Super Bowl Fever: What's Driving the Viral Craze?",
    "summary": "The Super Bowl, the biggest annual sporting event in the United States, has captured the nation's attention once again. Google searches for 'super bowl trending' have surged, indicating a widespread interest in the game and its cultural impact.",
    "origin_story": "The Super Bowl's popularity has been building for decades, but this year's event is particularly resonating on social media and search engines.",
    "expert_analysis": "The Super Bowl's status as a cultural phenomenon transcends the game itself. It's a time when brands, music, and even political discourse converge, making it a barometer for the pulse of American society. The trending search patterns reveal a deep-seated fascination with the event's ability to unite and captivate the nation.",
    "impact": "The Super Bowl's influence extends far beyond the field, shaping conversations, trends, and even the broader cultural landscape.",
    "status": "viral"
  },
  "timestamp": "2026-02-08T19:16:57.308884+00:00",
  "history": [
    {
      "timestamp": "2026-02-06T15:06:34.922295+00:00",
      "signal_score": 50
    },
    {
      "timestamp": "2026-02-06T17:32:05.598710+00:00",
      "signal_score": 50
    },
    {
      "timestamp": "2026-02-06T19:50:39.526592+00:00",
      "signal_score": 50
    },
    {
      "timestamp": "2026-02-06T21:04:44.481337+00:00",
      "signal_score": 50
    },
    {
      "timestamp": "2026-02-06T22:54:15.943340+00:00",
      "signal_score": 50
    },
    {
      "timestamp": "2026-02-07T07:11:38.554836+00:00",
      "signal_score": 50
    },
    {
      "timestamp": "2026-02-07T07:58:17.779856+00:00",
      "signal_score": 50
    },
    {
      "timestamp": "2026-02-07T09:03:33.267178+00:00",
      "signal_score": 50
    },
    {
      "timestamp": "2026-02-07T09:58:50.557038+00:00",
      "signal_score": 50
    },
    {
      "timestamp": "2026-02-07T11:59:55.371867+00:00",
      "signal_score": 50
    },
    {
      "timestamp": "2026-02-07T15:53:17.472901+00:00",
      "signal_score": 50
    },
    {
      "timestamp": "2026-02-07T17:20:07.936031+00:00",
      "signal_score": 50
    },
    {
      "timestamp": "2026-02-07T19:06:32.473235+00:00",
      "signal_score": 50
    },
    {
      "timestamp": "2026-02-07T19:50:11.707922+00:00",
      "signal_score": 50
    },
    {
      "timestamp": "2026-02-07T23:00:51.796573+00:00",
      "signal_score": 50
    },
    {
      "timestamp": "2026-02-08T05:42:02.940632+00:00",
      "signal_score": 50
    },
    {
      "timestamp": "2026-02-08T09:03:05.485715+00:00",
      "signal_score": 50
    },
    {
      "timestamp": "2026-02-08T09:59:29.333898+00:00",
      "signal_score": 50
    },
    {
      "timestamp": "2026-02-08T11:00:29.418945+00:00",
      "signal_score": 50
    },
    {
      "timestamp": "2026-02-08T11:48:30.961051+00:00",
      "signal_score": 50
    },
    {
      "timestamp": "2026-02-08T15:55:04.693917+00:00",
      "signal_score": 50
    },
    {
      "timestamp": "2026-02-08T17:02:58.093252+00:00",
      "signal_score": 50
    },
    {
      "timestamp": "2026-02-08T17:58:29.987357+00:00",
      "signal_score": 50
    },
    {
      "timestamp": "2026-02-08T19:16:57.308903+00:00",
      "signal_score": 50
    }
  ]
}