{
  "trend": "super bowl trending",
  "category": "sports",
  "platforms": {
    "google": true
  },
  "platform_count": 1,
  "metrics": {
    "google": {
      "searches": "155.7K",
      "raw": 155668
    },
    "x": {
      "posts": "0",
      "reposts": "0",
      "raw_posts": 0,
      "raw_reposts": 0
    },
    "tiktok": {
      "views": "0",
      "videos": "0",
      "raw_views": 0
    },
    "instagram": {
      "posts": "0",
      "reach": "0",
      "raw_posts": 0
    }
  },
  "signal_score": 50,
  "momentum": "stable",
  "lifecycle": "peak",
  "locations": [
    "global"
  ],
  "related_trends": [
    "super bowl trending",
    "super bowl trending twitter",
    "super bowl trending song"
  ],
  "analysis": {
    "headline": "Super Bowl Fever Grips the Internet as Fans Eagerly Await the Big Game",
    "summary": "The Super Bowl, one of the most anticipated sporting events of the year, is dominating online conversations as fans eagerly await the highly anticipated matchup. Google searches for 'super bowl trending' have spiked, indicating a growing interest in the upcoming game and related events.",
    "origin_story": "The surge in online chatter about the Super Bowl can be traced back to the official announcement of the teams and performers scheduled to participate in the event.",
    "expert_analysis": "The intense interest in the Super Bowl reflects the cultural significance of the event, which transcends the boundaries of sports. It's a time when fans come together to celebrate the pageantry, the commercials, and the shared experience of watching the biggest game of the year.",
    "impact": "The Super Bowl's trending status on Google is a testament to its enduring popularity and the way it captivates the attention of millions of people around the world.",
    "status": "rising"
  },
  "timestamp": "2026-02-06T22:54:15.943325+00:00",
  "history": [
    {
      "timestamp": "2026-02-06T11:14:00.482771+00:00",
      "signal_score": 50
    },
    {
      "timestamp": "2026-02-06T11:33:18.489184+00:00",
      "signal_score": 50
    },
    {
      "timestamp": "2026-02-06T12:21:15.305097+00:00",
      "signal_score": 50
    },
    {
      "timestamp": "2026-02-06T12:26:50.372998+00:00",
      "signal_score": 50
    },
    {
      "timestamp": "2026-02-06T15:06:34.922295+00:00",
      "signal_score": 50
    },
    {
      "timestamp": "2026-02-06T17:32:05.598710+00:00",
      "signal_score": 50
    },
    {
      "timestamp": "2026-02-06T19:50:39.526592+00:00",
      "signal_score": 50
    },
    {
      "timestamp": "2026-02-06T21:04:44.481337+00:00",
      "signal_score": 50
    },
    {
      "timestamp": "2026-02-06T22:54:15.943340+00:00",
      "signal_score": 50
    }
  ]
}