{
  "trend": "super bowl trending",
  "category": "sports",
  "platforms": {
    "google": true
  },
  "platform_count": 1,
  "metrics": {
    "google": {
      "searches": "189.0K",
      "raw": 188993
    },
    "x": {
      "posts": "0",
      "reposts": "0",
      "raw_posts": 0,
      "raw_reposts": 0
    },
    "tiktok": {
      "views": "0",
      "videos": "0",
      "raw_views": 0
    },
    "instagram": {
      "posts": "0",
      "reach": "0",
      "raw_posts": 0
    }
  },
  "signal_score": 50,
  "momentum": "stable",
  "lifecycle": "peak",
  "locations": [
    "global"
  ],
  "related_trends": [
    "super bowl trending",
    "super bowl trending twitter",
    "super bowl trending song"
  ],
  "analysis": {
    "headline": "Super Bowl Fever Sweeps the Internet as Game Day Approaches",
    "summary": "As the biggest annual sporting event in the US, the Super Bowl has the internet buzzing with excitement. Fans and non-fans alike are searching for the latest updates, predictions, and rumors surrounding the big game.",
    "origin_story": "The Super Bowl trend has been steadily building on Google as the championship game on February 12 draws near. Searches for terms like 'Super Bowl trending' and 'Super Bowl song' have spiked in the past week.",
    "expert_analysis": "The enduring popularity of the Super Bowl reflects America's deep-rooted love of football and the cultural significance of this iconic event. The Super Bowl transcends sports, becoming a shared experience that brings together people from all walks of life to celebrate, socialize, and enjoy the spectacle.",
    "impact": "The Super Bowl's viral trending status on Google underscores its status as a national obsession that captivates the attention of millions.",
    "status": "viral"
  },
  "timestamp": "2026-02-08T05:42:02.940617+00:00",
  "history": [
    {
      "timestamp": "2026-02-06T11:14:00.482771+00:00",
      "signal_score": 50
    },
    {
      "timestamp": "2026-02-06T11:33:18.489184+00:00",
      "signal_score": 50
    },
    {
      "timestamp": "2026-02-06T12:21:15.305097+00:00",
      "signal_score": 50
    },
    {
      "timestamp": "2026-02-06T12:26:50.372998+00:00",
      "signal_score": 50
    },
    {
      "timestamp": "2026-02-06T15:06:34.922295+00:00",
      "signal_score": 50
    },
    {
      "timestamp": "2026-02-06T17:32:05.598710+00:00",
      "signal_score": 50
    },
    {
      "timestamp": "2026-02-06T19:50:39.526592+00:00",
      "signal_score": 50
    },
    {
      "timestamp": "2026-02-06T21:04:44.481337+00:00",
      "signal_score": 50
    },
    {
      "timestamp": "2026-02-06T22:54:15.943340+00:00",
      "signal_score": 50
    },
    {
      "timestamp": "2026-02-07T07:11:38.554836+00:00",
      "signal_score": 50
    },
    {
      "timestamp": "2026-02-07T07:58:17.779856+00:00",
      "signal_score": 50
    },
    {
      "timestamp": "2026-02-07T09:03:33.267178+00:00",
      "signal_score": 50
    },
    {
      "timestamp": "2026-02-07T09:58:50.557038+00:00",
      "signal_score": 50
    },
    {
      "timestamp": "2026-02-07T11:59:55.371867+00:00",
      "signal_score": 50
    },
    {
      "timestamp": "2026-02-07T15:53:17.472901+00:00",
      "signal_score": 50
    },
    {
      "timestamp": "2026-02-07T17:20:07.936031+00:00",
      "signal_score": 50
    },
    {
      "timestamp": "2026-02-07T19:06:32.473235+00:00",
      "signal_score": 50
    },
    {
      "timestamp": "2026-02-07T19:50:11.707922+00:00",
      "signal_score": 50
    },
    {
      "timestamp": "2026-02-07T23:00:51.796573+00:00",
      "signal_score": 50
    },
    {
      "timestamp": "2026-02-08T05:42:02.940632+00:00",
      "signal_score": 50
    }
  ]
}