{
  "trend": "trump trending photo",
  "category": "politics",
  "platforms": {
    "google": true
  },
  "platform_count": 1,
  "metrics": {
    "google": {
      "searches": "232.6K",
      "raw": 232627
    },
    "x": {
      "posts": "0",
      "reposts": "0",
      "raw_posts": 0,
      "raw_reposts": 0
    },
    "tiktok": {
      "views": "0",
      "videos": "0",
      "raw_views": 0
    },
    "instagram": {
      "posts": "0",
      "reach": "0",
      "raw_posts": 0
    }
  },
  "signal_score": 50,
  "momentum": "stable",
  "lifecycle": "peak",
  "locations": [
    "global"
  ],
  "related_trends": [],
  "analysis": {
    "headline": "Trump's Latest Photo Sparks Renewed Fascination Across the Internet",
    "summary": "A new photo of former President Donald Trump has captured the attention of Google users, as people search to understand the context and significance behind this latest viral image.",
    "origin_story": "The photo, which has been widely shared on social media platforms, first emerged on various news and political websites, sparking a surge of online interest.",
    "expert_analysis": "This trend reflects the ongoing public fascination with Trump's political legacy and the continued scrutiny of his actions and public persona. The virality of the image suggests a desire among many to stay informed and engaged with the former president's activities, even as he has left office.",
    "impact": "The widespread interest in this photo could shape public discourse and influence the narrative around Trump's political future.",
    "status": "viral"
  },
  "timestamp": "2026-02-08T15:54:57.908969+00:00",
  "history": [
    {
      "timestamp": "2026-02-06T10:48:26.918171+00:00",
      "signal_score": 50
    },
    {
      "timestamp": "2026-02-06T11:08:52.316284+00:00",
      "signal_score": 50
    },
    {
      "timestamp": "2026-02-06T11:33:10.755431+00:00",
      "signal_score": 50
    },
    {
      "timestamp": "2026-02-06T11:47:54.288695+00:00",
      "signal_score": 50
    },
    {
      "timestamp": "2026-02-06T12:11:21.665371+00:00",
      "signal_score": 50
    },
    {
      "timestamp": "2026-02-08T11:00:21.820505+00:00",
      "signal_score": 50
    },
    {
      "timestamp": "2026-02-08T11:48:22.512275+00:00",
      "signal_score": 50
    },
    {
      "timestamp": "2026-02-08T13:59:17.884340+00:00",
      "signal_score": 50
    },
    {
      "timestamp": "2026-02-08T14:59:50.370631+00:00",
      "signal_score": 50
    },
    {
      "timestamp": "2026-02-08T15:54:57.908984+00:00",
      "signal_score": 50
    }
  ]
}