{
  "trend": "$ZRO",
  "category": "meme_coin",
  "platforms": {
    "coingecko": true,
    "crypto": true
  },
  "platform_count": 2,
  "metrics": {
    "market_cap_rank": 110,
    "price_btc": 2.7991332666961313e-05,
    "is_meme_coin": true,
    "engagement_score": 80
  },
  "signal_score": 90,
  "momentum": "rising",
  "lifecycle": "new",
  "locations": [
    "global"
  ],
  "related_trends": [],
  "source": "coingecko_trending",
  "influencer": null,
  "tweet_url": null,
  "cashtags": [
    "$ZRO"
  ],
  "hashtags": [],
  "analysis": {
    "headline": "$ZRO Surges as Degens Fomo Into Meme Coin Craze",
    "summary": "The low-cap meme coin $ZRO has seen a massive price surge as traders pile in, attracted by its skyrocketing social engagement. This latest crypto trend is generating major FOMO among retail investors seeking outsized gains.",
    "origin_story": "The $ZRO token first gained traction on CoinGecko and other crypto platforms, fueled by coordinated shilling from a growing community of meme coin enthusiasts.",
    "expert_analysis": "With a high engagement score and 'meme coin' status, $ZRO is clearly capturing the imagination of the crypto degen crowd. The recent price action suggests this could be the start of a full-blown 'meme coin season' as traders look to ride the wave of hype and volatility.",
    "impact": "A flood of new money has poured into $ZRO, driving up trading volume and market cap rapidly.",
    "status": "viral"
  },
  "timestamp": "2026-02-10T07:58:33.274763+00:00",
  "history": [
    {
      "timestamp": "2026-02-10T07:32:15.947886+00:00",
      "signal_score": 90
    },
    {
      "timestamp": "2026-02-10T07:41:59.643230+00:00",
      "signal_score": 90
    },
    {
      "timestamp": "2026-02-10T07:58:33.274782+00:00",
      "signal_score": 90
    }
  ]
}